LICENSE.txt
MANIFEST.in
README.md
setup.cfg
setup.py
bin/tstat_cull
bin/tstat_send
tstat_transport/__init__.py
tstat_transport/common.py
tstat_transport/format.py
tstat_transport/parse.py
tstat_transport/transport.py
tstat_transport/util.py
tstat_transport.egg-info/PKG-INFO
tstat_transport.egg-info/SOURCES.txt
tstat_transport.egg-info/dependency_links.txt
tstat_transport.egg-info/requires.txt
tstat_transport.egg-info/top_level.txt