Metadata-Version: 1.1
Name: tstat-transport
Version: 0.6.4
Summary: Tools to send Tstat (TCP STatistic and Analysis Tool) log data to archive servers.
Home-page: https://github.com/esnet/tstat-transport
Author: Monte M. Goode
Author-email: MMGoode@lbl.gov
License: UNKNOWN
Platform: UNKNOWN
Classifier: Development Status :: 5 - Production/Stable
Classifier: Intended Audience :: Developers
Classifier: Intended Audience :: Telecommunications Industry
Classifier: Environment :: Console
Classifier: License :: OSI Approved :: BSD License
Classifier: Operating System :: POSIX
Classifier: Programming Language :: Python :: 2
Classifier: Programming Language :: Python :: 3
Classifier: Topic :: Internet
Classifier: Topic :: System :: Networking
Classifier: Topic :: Software Development :: Libraries
